{
    "monstersLevel1": [
        {
            "name": "Demons",
            "img": "/monsters/level 1/demons.png",
            "drop": 1,
            "health": 3,
            "defense": 1,
            "action": "COMBAT 1 <span class=\"custom-font special\">e</span> : Attacking or defending Hero discards 1 <span class=\"custom-font mana\">c</span>."
        },
        {
            "name": "Undead",
            "img": "/monsters/level 1/undead.png",
            "drop": 1,
            "health": 4,
            "defense": 0,
            "action": "ATTACK 1 <span class=\"custom-font special\">e</span> : +1 <span class=\"custom-font die-yellow\">s</span> and this Mob takes 2 Wounds."
        },
        {
            "name": "Fire Entities",
            "img": "/monsters/level 1/fire_entities.png",
            "drop": 1,
            "health": 3,
            "defense": 1,
            "action": "COMBAT 1 <span class=\"custom-font special\">e</span> : Add 1 <span class=\"custom-font die-yellow\">h</span> to the attacking or defenfing Hero."
        },
        {
            "name": "Fallen Angels",
            "img": "/monsters/level 1/fallen_angels.png",
            "drop": 1,
            "health": 2,
            "defense": 2,
            "action": "ATTACK 1 <span class=\"custom-font special\">e</span> : Defender -1 <span class=\"custom-font mana\">b</span>."
        },
        {
            "name": "Satyrs",
            "img": "/monsters/level 1/satyrs.png",
            "drop": 1,
            "health": 3,
            "defense": 1,
            "action": "ATTACK 1 <span class=\"custom-font special\">e</span> : +1 <span class=\"custom-font mana\">a</span>."
        },
        {
            "name": "Gargoyles",
            "img": "/monsters/level 1/gargoyles.png",
            "drop": 1,
            "health": 2,
            "defense": 1,
            "action": "DEFENSE 1 <span class=\"custom-font special\">e</span> : +1 <span class=\"custom-font mana\">b</span>."
        },
        {
            "name": "Infernal Imps",
            "img": "/monsters/level 1/infernal_imps.png",
            "drop": 1,
            "health": 3,
            "defense": 1,
            "action": "DEFENSE 1 <span class=\"custom-font special\">e</span> : Kill 1 Imp. Then, deal 1 Wound to each Hero in the attacker's Zone (once per roll)"
        },
        {
            "name": "Skeletons",
            "img": "/monsters/level 1/skeletons.png",
            "drop": 1,
            "health": 2,
            "defense": 1,
            "action": "DEFENSE 2 <span class=\"custom-font special\">e</span> : Add 1 Skeleton Minion to this Mob (if possible) unless the attacking Hero discards 1 <span class=\"custom-font mana\">c</span>."
        }
    ],
    "monstersLevel3": [
        {
            "name": "Demons",
            "img": "/monsters/level 3/demons.png",
            "drop": 1,
            "health": 4,
            "defense": 2,
            "action": "COMBAT 1 <span class=\"custom-font special\">e</span> : Attacking or defending Hero discards 1 <span class=\"custom-font mana\">c</span>."
        },
        {
            "name": "Undead",
            "img": "/monsters/level 3/undead.png",
            "drop": 1,
            "health": 5,
            "defense": 0,
            "action": "ATTACK 1 <span class=\"custom-font special\">e</span> : +2 <span class=\"custom-font die-yellow\">s</span> and this Mob takes 2 Wounds."
        },
        {
            "name": "Fire Entities",
            "img": "/monsters/level 3/fire_entities.png",
            "drop": 1,
            "health": 4,
            "defense": 2,
            "action": "COMBAT 1 <span class=\"custom-font special\">e</span> : Add 1 <span class=\"custom-font die-yellow\">h</span> to the attacking or defenfing Hero."
        },
        {
            "name": "Fallen Angels",
            "img": "/monsters/level 3/fallen_angels.png",
            "drop": 1,
            "health": 3,
            "defense": 3,
            "action": "ATTACK 1 <span class=\"custom-font special\">e</span> : Defender -2 <span class=\"custom-font mana\">b</span>."
        },
        {
            "name": "Satyrs",
            "img": "/monsters/level 3/satyrs.png",
            "drop": 1,
            "health": 4,
            "defense": 2,
            "action": "ATTACK 1 <span class=\"custom-font special\">e</span> : +2 <span class=\"custom-font mana\">a</span>."
        },
        {
            "name": "Gargoyles",
            "img": "/monsters/level 3/gargoyles.png",
            "drop": 1,
            "health": 3,
            "defense": 2,
            "action": "DEFENSE 1 <span class=\"custom-font special\">e</span> : +1 <span class=\"custom-font mana\">b</span>."
        },
        {
            "name": "Infernal Imps",
            "img": "/monsters/level 3/infernal_imps.png",
            "drop": 1,
            "health": 4,
            "defense": 1,
            "action": "DEFENSE 1 <span class=\"custom-font special\">e</span> : Kill 1 Imp. Then, deal 2 Wound to each Hero in the attacker's Zone (once per roll)"
        },
        {
            "name": "Skeletons",
            "img": "/monsters/level 3/skeletons.png",
            "drop": 1,
            "health": 3,
            "defense": 2,
            "action": "DEFENSE 2 <span class=\"custom-font special\">e</span> : Add 1 Skeleton Minion to this Mob (if possible) unless the attacking Hero discards 1 <span class=\"custom-font mana\">c</span>."
        }
    ],
    "monstersLevel5": [
        {
            "name": "Demons",
            "img": "/monsters/level 5/demons.png",
            "drop": 2,
            "health": 6,
            "defense": 4,
            "action": "COMBAT 1 <span class=\"custom-font special\">e</span> : Attacking or defending Hero discards 1 <span class=\"custom-font mana\">c</span>."
        },
        {
            "name": "Undead",
            "img": "/monsters/level 5/undead.png",
            "drop": 2,
            "health": 8,
            "defense": 0,
            "action": "ATTACK 1 <span class=\"custom-font special\">e</span> : +1 <span class=\"custom-font die-yellow\">s</span> +1 <span class=\"custom-font die-orange\">s</span> and this Mob takes 2 Wounds."
        },
        {
            "name": "Fire Entities",
            "img": "/monsters/level 5/fire_entities.png",
            "drop": 2,
            "health": 7,
            "defense": 3,
            "action": "COMBAT 1 <span class=\"custom-font special\">e</span> : Add 1 <span class=\"custom-font die-yellow\">h</span> to the attacking or defenfing Hero."
        },
        {
            "name": "Fallen Angels",
            "img": "/monsters/level 5/fallen_angels.png",
            "drop": 2,
            "health": 5,
            "defense": 5,
            "action": "ATTACK 1 <span class=\"custom-font special\">e</span> : Defender -2 <span class=\"custom-font mana\">b</span>."
        },
        {
            "name": "Satyrs",
            "img": "/monsters/level 5/satyrs.png",
            "drop": 2,
            "health": 6,
            "defense": 4,
            "action": "ATTACK 1 <span class=\"custom-font special\">e</span> : +2 <span class=\"custom-font mana\">a</span>."
        },
        {
            "name": "Gargoyles",
            "img": "/monsters/level 5/gargoyles.png",
            "drop": 2,
            "health": 6,
            "defense": 3,
            "action": "DEFENSE 1 <span class=\"custom-font special\">e</span> : +2 <span class=\"custom-font mana\">b</span>."
        },
        {
            "name": "Infernal Imps",
            "img": "/monsters/level 5/infernal_imps.png",
            "drop": 2,
            "health": 5,
            "defense": 3,
            "action": "DEFENSE 1 <span class=\"custom-font special\">e</span> : Kill 1 Imp. Then, deal 3 Wound to each Hero in the attacker's Zone (once per roll)"
        },
        {
            "name": "Skeletons",
            "img": "/monsters/level 5/skeletons.png",
            "drop": 2,
            "health": 5,
            "defense": 4,
            "action": "DEFENSE 1 <span class=\"custom-font special\">e</span> : Add 1 Skeleton Minion to this Mob (if possible) unless the attacking Hero discards 2 <span class=\"custom-font mana\">c</span>."
        }
    ],
    "roamingMonsterLevel1": [
        {
            "name": "Lyidan, Incubus Lord",
            "img": "/roaming-monsters/level 1/Lyidan.png",
            "health": "7",
            "drop": 2,
            "rareDrop": 1,
            "defense": {
                "blueDie": 2,
                "blackDie": 1
            },
            "closeAttack": {
                "orangeDie": 1,
                "blackDie": 2
            },
            "action": "<b>If Lyidan is in a Light Zone: </b>Lyidan takes 3 Wounds and moves to the closest Shadow Zone.",
            "action2": "<b>If there is a Hero up to 3 Zones away <i>(regardless of LoS): </i></b>Place Lyidan in the Zone with the furthest Hero up to 3 Zones away <i>(regardless of LoS).</i> Add 1 <span class=\"custom-font die-yellow\">h</span> to that Hero and attack them.",
            "action3": "ATTACK 1 <span class=\"custom-font special\">e</span> : After combat, resolve all <span class=\"custom-font die-yellow\">h</span> on the defending Hero (once per combat)."
        },
        {
            "name": "Ytheria, Undead Queen",
            "img": "/roaming-monsters/level 1/Ytheria.png",
            "health": "4",
            "drop": 2,
            "rareDrop": 1,
            "defense": {
                "blueDie": 1,
                "blackDie": 1
            },
            "closeAttack": {
                "yellowDie": 1
            },
            "rangeAttack": {
                "yellowDie": 2,
                "blackDie": 1
            },
            "action": "<b>If there is more than 1 Hero in LoS:</b> Ytheria attacks each Hero in LoS <i>(resolve each attack seperately)</i>",
            "action2": "<b>If there is only 1 Hero in LoS:</b> Ytheria attacks that Hero with +1 <span class=\"custom-font die-orange\">s</span>",
            "action3": "ATTACK 1 <span class=\"custom-font special\">e</span> : Add 1 Minion to each Mob in the Dungeon, if possible."
        },
        {
            "name": "Andra",
            "img": "/roaming-monsters/level 1/Andra.png",
            "health": "5",
            "drop": 2,
            "rareDrop": 1,
            "defense": {
                "blueDie": 2,
                "blackDie": 1
            },
            "closeAttack": {
                "yellowDie": 1,
                "blackDie": 1
            },
            "rangeAttack": {
                "yellowDie": 1,
                "blackDie": 1
            },
            "action": "<b>If Andra is in the Dungeon:</b> Andra attack the Hero with the lowest Health in LoS, if possible. Then, remove Andra from the Dungeon.",
            "action2": "<b>If Andra is not in the Dungeon:</b> Place Andra in a Zone adjacent to the Hero with the lowest Health. Then Andra attacks that Hero.",
            "action3": "COMBAT 1 <span class=\"custom-font special\">e</span> : Deal 1 Wound to another Hero with the lowest Health in LoS."
        },
        {
            "name": "The Ghoul",
            "img": "/roaming-monsters/level 1/The Ghoul.png",
            "health": "5",
            "drop": 2,
            "rareDrop": 1,
            "defense": {
                "blueDie": 2,
                "blackDie": 1
            },
            "closeAttack": {
                "orangeDie": 1,
                "blackDie": 1
            },
            "action": "<b>If there is a Minion in the Ghoul's Zone:</b> Kill 1 Minion in that Zone <i>(players choose)</i> and The Ghoul Heals 5.",
            "action2": "<b>Otherwise:</b> The Ghoul moves 3 Zones toward the closest Hero and attacks them, if possible.",
            "action3": "COMBAT 1 <span class=\"custom-font special\">e</span> : Move the closest Mob 1 Zone toward The Ghoul."
        }
    ],
    "roamingMonsterLevel3": [
        {
            "name": "Lyidan, Incubus Lord",
            "img": "/roaming-monsters/level 3/Lyidan.png",
            "health": "10",
            "drop": 2,
            "epicDrop": 1,
            "defense": {
                "blueDie": 2,
                "blackDie": 1
            },
            "closeAttack": {
                "orangeDie": 2,
                "blackDie": 1
            },
            "action": "<b>If Lyidan is in a Light Zone: </b>Lyidan takes 5 Wounds and moves to the closest Shadow Zone.",
            "action2": "<b>If there is a Hero up to 3 Zones away <i>(regardless of LoS): </i></b>Place Lyidan in the Zone with the furthest Hero up to 3 Zones away <i>(regardless of LoS).</i> Add 1 <span class=\"custom-font die-yellow\">h</span> to that Hero and attack them.",
            "action3": "ATTACK 1 <span class=\"custom-font special\">e</span> : After combat, resolve all <span class=\"custom-font die-yellow\">h</span> on the defending Hero using <span class=\"custom-font die-orange\">s</span> instead (once per combat)."
        },
        {
            "name": "Ytheria, Undead Queen",
            "img": "/roaming-monsters/level 3/Ytheria.png",
            "health": "6",
            "drop": 2,
            "epicDrop": 1,
            "defense": {
                "blueDie": 2,
                "blackDie": 1
            },
            "closeAttack": {
                "orangeDie": 1
            },
            "rangeAttack": {
                "yellowDie": 1,
				"orangeDie": 1,
                "blackDie": 1
            },
            "action": "<b>If there is more than 1 Hero in LoS:</b> Ytheria attacks each Hero in LoS <i>(resolve each attack seperately)</i>",
            "action2": "<b>If there is only 1 Hero in LoS:</b> Ytheria attacks that Hero with +1 <span class=\"custom-font die-yellow\">s</span> +1 <span class=\"custom-font die-orange\">s</span>",
            "action3": "ATTACK 1 <span class=\"custom-font special\">e</span> : Add 1 Minion to each Mob in the Dungeon, if possible."
        },
        {
            "name": "Andra",
            "img": "/roaming-monsters/level 3/Andra.png",
            "health": "7",
            "drop": 2,
            "epicDrop": 1,
            "defense": {
                "blueDie": 3,
                "blackDie": 1
            },
            "closeAttack": {
                "yellowDie": 1,
				"orangeDie": 1,
                "blackDie": 1
            },
            "rangeAttack": {
                "yellowDie": 1,
				"orangeDie": 1,
                "blackDie": 1
            },
            "action": "<b>If Andra is in the Dungeon:</b> Andra attack the Hero with the lowest Health in LoS, if possible. Then, remove Andra from the Dungeon.",
            "action2": "<b>If Andra is not in the Dungeon:</b> Place Andra in a Zone adjacent to the Hero with the lowest Health. Then Andra attacks that Hero.",
            "action3": "COMBAT 1 <span class=\"custom-font special\">e</span> : Deal 2 Wound to another Hero with the lowest Health in LoS."
        },
        {
            "name": "The Ghoul",
            "img": "/roaming-monsters/level 3/The Ghoul.png",
            "health": "8",
            "drop": 2,
            "epicDrop": 1,
            "defense": {
                "blueDie": 3,
                "blackDie": 1
            },
            "closeAttack": {
                "orangeDie": 2,
                "blackDie": 2
            },
            "action": "<b>If there is a Minion in the Ghoul's Zone:</b> Kill 1 Minion in that Zone <i>(players choose)</i> and The Ghoul Heals 8.",
            "action2": "<b>Otherwise:</b> The Ghoul moves 3 Zones toward the closest Hero and attacks them, if possible.",
            "action3": "COMBAT 1 <span class=\"custom-font special\">e</span> : Move the closest Mob 1 Zone toward The Ghoul."
        }
    ],
    "roamingMonsterLevel5": [
        {
            "name": "Lyidan, Incubus Lord",
            "img": "/roaming-monsters/level 5/Lyidan.png",
            "health": "12",
            "epicDrop": 3,
            "defense": {
                "blueDie": 4,
                "blackDie": 1
            },
            "closeAttack": {
				"yellowDie": 2,
                "orangeDie": 2,
                "blackDie": 1
            },
            "action": "<b>If Lyidan is in a Light Zone: </b>Lyidan takes 6 Wounds and moves to the closest Shadow Zone.",
            "action2": "<b>If there is a Hero up to 3 Zones away <i>(regardless of LoS): </i></b>Place Lyidan in the Zone with the furthest Hero up to 3 Zones away <i>(regardless of LoS).</i> Add 2 <span class=\"custom-font die-yellow\">h</span> to that Hero and attack them.",
            "action3": "ATTACK 1 <span class=\"custom-font special\">e</span> : After combat, resolve all <span class=\"custom-font die-yellow\">h</span> on the defending Hero using <span class=\"custom-font die-orange\">s</span> instead (once per combat)."
        },
        {
            "name": "Ytheria, Undead Queen",
            "img": "/roaming-monsters/level 5/Ytheria.png",
            "health": "8",
            "epicDrop": 3,
            "defense": {
                "blueDie": 4,
                "blackDie": 1
            },
            "closeAttack": {
                "yellowDie": 2,
				"orangeDie": 1
            },
            "rangeAttack": {
                "yellowDie": 2,
				"orangeDie": 1,
                "blackDie": 1
            },
            "action": "<b>If there is more than 1 Hero in LoS:</b> Ytheria attacks each Hero in LoS <i>(resolve each attack seperately)</i>",
            "action2": "<b>If there is only 1 Hero in LoS:</b> Ytheria attacks that Hero with +2 <span class=\"custom-font die-orange\">s</span>",
            "action3": "ATTACK 1 <span class=\"custom-font special\">e</span> : Add 1 Minion to each Mob in the Dungeon, if possible."
        },
        {
            "name": "Andra",
            "img": "/roaming-monsters/level 5/Andra.png",
            "health": "10",
            "epicDrop": 3,
            "defense": {
                "blueDie": 5,
                "blackDie": 1
            },
            "closeAttack": {
                "yellowDie": 1,
				"orangeDie": 2,
                "blackDie": 1
            },
            "rangeAttack": {
                "yellowDie": 1,
				"orangeDie": 2,
                "blackDie": 1
            },
            "action": "<b>If Andra is in the Dungeon:</b> Andra attack the Hero with the lowest Health in LoS, if possible. Then, remove Andra from the Dungeon.",
            "action2": "<b>If Andra is not in the Dungeon:</b> Place Andra in a Zone adjacent to the Hero with the lowest Health. Then Andra attacks that Hero.",
            "action3": "COMBAT 1 <span class=\"custom-font special\">e</span> : Deal 2 Wound to another Hero with the lowest Health in LoS."
        },
        {
            "name": "The Ghoul",
            "img": "/roaming-monsters/level 5/The Ghoul.png",
            "health": "10",
            "epicDrop": 3,
            "defense": {
                "blueDie": 4,
                "blackDie": 1
            },
            "closeAttack": {
                "orangeDie": 3,
                "blackDie": 3
            },
            "action": "<b>If there is a Minion in the Ghoul's Zone:</b> Kill 1 Minion in that Zone <i>(players choose)</i> and The Ghoul Heals 10.",
            "action2": "<b>Otherwise:</b> The Ghoul moves 3 Zones toward the closest Hero and attacks them, if possible.",
            "action3": "COMBAT 1 <span class=\"custom-font special\">e</span> : Move the closest Mob 1 Zone toward The Ghoul."
        }
    ]
}